panars/__init__.py
panars/dataframe.py
panars/io.py
panars/series.py
panars/utils.py
panars-0.1.2.dist-info/LICENSE
panars-0.1.2.dist-info/METADATA
panars-0.1.2.dist-info/WHEEL
panars-0.1.2.dist-info/top_level.txt
panars-0.1.2.dist-info/RECORD
