Metadata-Version: 2.1
Name: panars
Version: 0.1.2
Summary: Default template for PDM package
Author-email: milisp <milisp@proton.me>
License: MIT
Requires-Python: ==3.12.*
License-File: LICENSE
Requires-Dist: polars>=1.10.0
Requires-Dist: pyarrow>=7.0.0
Requires-Dist: xlsxwriter
Requires-Dist: pandas
Provides-Extra: calamine
Requires-Dist: fastexcel>=0.9; extra == "calamine"
Provides-Extra: excel
Requires-Dist: polars[calamine,openpyxl,xlsx2csv,xlsxwriter]; extra == "excel"
Provides-Extra: numpy
Requires-Dist: numpy>=1.16.0; extra == "numpy"
Provides-Extra: openpyxl
Requires-Dist: openpyxl>=3.0.0; extra == "openpyxl"
Provides-Extra: pandas
Requires-Dist: pandas; extra == "pandas"
Requires-Dist: polars[pyarrow]; extra == "pandas"
Provides-Extra: pyarrow
Requires-Dist: pyarrow>=7.0.0; extra == "pyarrow"
Provides-Extra: pydantic
Requires-Dist: pydantic; extra == "pydantic"
Provides-Extra: xlsx2csv
Requires-Dist: xlsx2csv>=0.8.0; extra == "xlsx2csv"
Provides-Extra: xlsxwriter
Requires-Dist: xlsxwriter; extra == "xlsxwriter"
